{"time":{"updated":"Dec 13, 2024 01:53:39 UTC","updatedISO":"2024-12-13T01:53:39+00:00","updateduk":"Dec 13, 2024 at 01:53 GMT"},"disclaimer":"This data was produced from the CoinDesk Bitcoin Price Index (USD). Non-USD currency data converted using hourly conversion rate from openexchangerates.org","chartName":"Bitcoin","bpi":{"USD":{"code":"USD","symbol":"&#36;","rate":"99,768.485","description":"United States Dollar","rate_float":99768.4851},"GBP":{"code":"GBP","symbol":"&pound;","rate":"78,066.146","description":"British Pound Sterling","rate_float":78066.1459},"EUR":{"code":"EUR","symbol":"&euro;","rate":"94,735.165","description":"Euro","rate_float":94735.165},"CNY":{"code":"CNY","symbol":"&yen;","rate":"723,291.587","description":"Chinese Yuan","rate_float":723291.5865}}}